Metadata-Version: 1.1
Name: ckanext-datasetthumbnail
Version: 1.0.1
Summary: Generates thumbnails for datasets.
Home-page: https://github.com/aptivate/ckanext-datasetthumbnail
Author: Aptivate
Author-email: info@aptivate.org
License: AGPL
Keywords: CKAN thumbnail
Platform: UNKNOWN
Classifier: Development Status :: 4 - Beta
Classifier: License :: OSI Approved :: GNU Affero General Public License v3 or later (AGPLv3+)
Classifier: Programming Language :: Python :: 2.6
Classifier: Programming Language :: Python :: 2.7
